{
  "feature_names": [
    "acc_mag_std",
    "step_band_power_ratio",
    "step_band_peak_hz",
    "gyro_mag_mean",
    "gyro_mag_std",
    "gyro_mag_max",
    "acc_mag_mean",
    "acc_mag_max",
    "acc_mag_min",
    "log_spec_0p5_1p1",
    "log_spec_1p1_2p2",
    "log_spec_2p2_4"
  ],
  "window_s": 2.0,
  "stride_s": 1.0,
  "target_fs": 40.0,
  "classes": [
    "running",
    "standing",
    "walking"
  ],
  "n_windows": 110,
  "n_features": 12,
  "labeled_root": "/home/bernard/Downloads/metawear-baro-tools-master/labeled_data"
}